imagem_processamento/__init__.py
imagem_processamento/processing/__init__.py
imagem_processamento/processing/combination.py
imagem_processamento/processing/transformation.py
imagem_processamento/utils/__init__.py
imagem_processamento/utils/io.py
imagem_processamento/utils/plot.py
imagem_processamento-0.0.1.dist-info/METADATA
imagem_processamento-0.0.1.dist-info/WHEEL
imagem_processamento-0.0.1.dist-info/top_level.txt
imagem_processamento-0.0.1.dist-info/RECORD
