Metadata-Version: 2.1
Name: imagem-processamento
Version: 0.0.1
Summary: My short description
Home-page: https://github.com/jeromario/image-processing-package
Author: Jefferson Andrade
Author-email: jeffersonjla@hotmail.com
License: UNKNOWN
Platform: UNKNOWN
Requires-Python: >=3.8
Requires-Dist: matplotlib
Requires-Dist: numpy
Requires-Dist: scikit-image (>=0.16.1)
